Metadata-Version: 2.1
Name: odoo-addon-base_optional_quick_create
Version: 18.0.1.0.0.2
Requires-Python: >=3.10
Requires-Dist: odoo==18.0.*
Summary: Avoid "quick create" on m2o fields, on a "by model" basis
Home-page: https://github.com/OCA/server-ux
License: AGPL-3
Author: Agile Business Group,Odoo Community Association (OCA)
Author-email: support@odoo-community.org
Classifier: Programming Language :: Python
Classifier: Framework :: Odoo
Classifier: Framework :: Odoo :: 18.0
Classifier: License :: OSI Approved :: GNU Affero General Public License v3
